setup.cfg
setup.py
celery_multibeat.egg-info/PKG-INFO
celery_multibeat.egg-info/SOURCES.txt
celery_multibeat.egg-info/dependency_links.txt
celery_multibeat.egg-info/requires.txt
celery_multibeat.egg-info/top_level.txt
multibeat/__init__.py
multibeat/decoders.py
multibeat/schedulers.py