Metadata-Version: 1.1
Name: celery-multibeat
Version: 0.0.1
Summary: A Distributed Celery Beat Scheduler built on Redis
Home-page: https://github.com/rhockenbury/multibeat
Author: Ryler Hockenbury
Author-email: ryler.hockenbury@gmail.com
License: Apache License, Version 2.0
Download-URL: https://github.com/rhockenbury/multibeat/tarball/0.0.1
Keywords: celerybeat,celery,beat,distributed,redis,lock
Platform: UNKNOWN
